optimModels/__init__.py
optimModels/comm_optim/CModel.py
optimModels/comm_optim/__init__.py
optimModels/comm_optim/ea_knockout.py
optimModels/comm_optim/ea_setup.py
optimModels/examples/models/Achromobacter_xylosoxidans_A8.xml
optimModels/examples/models/Achromobacter_xylosoxidans_NBRC_15126.xml
optimModels/examples/models/Acidaminococcus_intestini_RyC_MR95.xml
optimModels/examples/models/Acidaminococcus_sp_D21.xml
optimModels/examples/models/Acinetobacter_calcoaceticus_PHEA_2.xml
optimModels/examples/models/Acinetobacter_junii_SH205.xml
optimModels/examples/models/Acinetobacter_lwoffii_WJ10621.xml
optimModels/examples/models/Actinobacillus_pleuropneumoniae_L20.xml
optimModels/examples/models/Clostridiales_sp_1_7_47FAA.xml
optimModels/examples/models/E_coli_Millard2016v2.xml
optimModels/examples/models/Ec_iAF1260.xml
optimModels/examples/models/Millard2016v2.xml
optimModels/examples/models/Yokenella_regensburgei_ATCC_43003.xml
optimModels/examples/models/chassagnole2002.xml
optimModels/examples/models/yeastGEM.xml
optimModels/examples/models/yeastGEMv8_46_4.xml
optimModels/examples/models/yeast_7.6.xml
optimModels/model/__init__.py
optimModels/model/kineticModel.py
optimModels/optimization/__init__.py
optimModels/optimization/decoders.py
optimModels/optimization/evaluation_functions.py
optimModels/optimization/evaluators.py
optimModels/optimization/evolutionary_computation.py
optimModels/optimization/generators.py
optimModels/optimization/observers.py
optimModels/optimization/replacers.py
optimModels/optimization/run.py
optimModels/optimization/variators.py
optimModels/simulation/__init__.py
optimModels/simulation/analysis.py
optimModels/simulation/override_simul_problem.py
optimModels/simulation/run.py
optimModels/simulation/simul_problems.py
optimModels/simulation/simul_results.py
optimModels/simulation/solvers.py
optimModels/unittests/__init__.py
optimModels/unittests/comm_optim.py
optimModels/unittests/gecko_optim.py
optimModels/unittests/gecko_simul.py
optimModels-0.0.16.dist-info/LICENSE
optimModels-0.0.16.dist-info/METADATA
optimModels-0.0.16.dist-info/WHEEL
optimModels-0.0.16.dist-info/top_level.txt
optimModels-0.0.16.dist-info/RECORD
