Metadata-Version: 2.1
Name: optimModels
Version: 0.0.16
Summary: optimModels - strain optimization
Home-page: https://github.com/saragcorreia/optimModels.git
Author: Sara Correia
Author-email: sarag.correia@gmail.com
License: Apache License Version 2.0
Keywords: strain design
Platform: UNKNOWN
Classifier: Topic :: Utilities
Classifier: Programming Language :: Python :: 3.6
Requires-Dist: inspyred
Requires-Dist: framed
Requires-Dist: geckopy
Requires-Dist: cobra
Requires-Dist: optlang
Requires-Dist: pandas
Requires-Dist: numpy
